{
  "components": [
    "ControlComponent",
    "PositionComponent",
    "EnergyComponent",
    "CreationBlockComponent",
    "ReadyBlockComponent",
    "InventoryComponent",
    "MatterComponent",
    "PortableComponent"
  ],
  "systems": [
    {
      "name": "ComponentDevSystem",
      "writeAccess": [
        "*"
      ]
    },
    {
      "name": "SpawnSystem",
      "writeAccess": [
        "ControlComponent",
        "PositionComponent",
        "EnergyComponent",
        "CreationBlockComponent",
        "ReadyBlockComponent",
        "InventoryComponent",
        "PortableComponent"
      ]
    }
  ]
}